stempelwerk/StempelWerk.py
stempelwerk/__init__.py
stempelwerk-1.1.0.dist-info/METADATA
stempelwerk-1.1.0.dist-info/WHEEL
stempelwerk-1.1.0.dist-info/entry_points.txt
stempelwerk-1.1.0.dist-info/licenses/LICENSE.md
stempelwerk-1.1.0.dist-info/RECORD
