Metadata-Version: 2.4
Name: StempelWerk
Version: 1.1.0
Summary: Automatic code generation from Jinja2 templates
Project-URL: Homepage, https://github.com/mzuther/StempelWerk
Project-URL: Repository, https://github.com/mzuther/StempelWerk.git
Project-URL: Changelog, https://github.com/mzuther/StempelWerk/blob/develop/CHANGELOG.md
Author-email: Martin Zuther <code@mzuther.de>
License-Expression: BSD-3-Clause
License-File: LICENSE.md
Keywords: code generation,jinja,lean,metaprogramming,powerful,template
Classifier: Development Status :: 5 - Production/Stable
Classifier: Environment :: Console
Classifier: Intended Audience :: Developers
Classifier: License :: OSI Approved :: BSD License
Classifier: Operating System :: OS Independent
Classifier: Programming Language :: Python :: 3
Classifier: Topic :: Software Development :: Code Generators
Classifier: Topic :: Software Development :: Libraries :: Python Modules
Classifier: Topic :: Software Development :: Pre-processors
Classifier: Topic :: Text Processing
Classifier: Topic :: Utilities
Requires-Python: <4.0,>=3.10
Requires-Dist: herkules<2,>=1.0.0
Requires-Dist: jinja2<4,>=3.1.6
